subtitles_translator/__init__.py
subtitles_translator/available_languages.py
subtitles_translator/cli.py
subtitles_translator/ffmpeg_utils.py
subtitles_translator/subtitles.py
subtitles_translator/translator.py
subtitles_translator-0.0.3.dist-info/LICENSE
subtitles_translator-0.0.3.dist-info/METADATA
subtitles_translator-0.0.3.dist-info/WHEEL
subtitles_translator-0.0.3.dist-info/entry_points.txt
subtitles_translator-0.0.3.dist-info/RECORD
