Metadata-Version: 2.1
Name: subtitles-translator
Version: 0.0.3
Summary: Automatic subtitles translation with a local neural machine translation model. No third-party service required: the translation is done locally with small but efficient neural network models.
Home-page: https://github.com/tdhm/subtitles-translator
Author: TDHM
Author-email: tdhm-git@outlook.com
Requires-Python: >=3.8,<3.11
Classifier: Programming Language :: Python :: 3
Classifier: Programming Language :: Python :: 3.8
Classifier: Programming Language :: Python :: 3.9
Classifier: Programming Language :: Python :: 3.10
Requires-Dist: sentencepiece (>=0.1.97,<0.2.0)
Requires-Dist: torch (==2.0.0)
Requires-Dist: transformers (>=4.27.2,<5.0.0)
Project-URL: Documentation, https://tdhm.github.io/subtitles-translator/
Project-URL: Repository, https://github.com/tdhm/subtitles-translator
